freeproxies/__init__.py
freeproxies/__version__.py
freeproxies/freeproxies.py
freeproxies-0.0.1.dist-info/LICENSE
freeproxies-0.0.1.dist-info/METADATA
freeproxies-0.0.1.dist-info/WHEEL
freeproxies-0.0.1.dist-info/top_level.txt
freeproxies-0.0.1.dist-info/RECORD
