Metadata-Version: 2.1
Name: freeproxies
Version: 0.0.1
Summary: Free proxies for humans
Home-page: https://github.com/iamkamleshrangi/freeproxies
Author: Kamlesh Kumar Rangi
Author-email: iamkamleshrangi@gmail.com
License: UNKNOWN
Project-URL: Source, https://github.com/iamkamleshrangi/freeproxies
Platform: UNKNOWN
Classifier: Development Status :: 5 - Production/Stable
Classifier: Intended Audience :: Developers
Classifier: Natural Language :: English
Classifier: License :: OSI Approved :: GNU General Public License v3 (GPLv3)
Classifier: Programming Language :: Python
Classifier: Programming Language :: Python :: 3
Requires-Python: >=3.6
